odoo/addons/account_move_line_contra_accounts/LICENSE
odoo/addons/account_move_line_contra_accounts/README.rst
odoo/addons/account_move_line_contra_accounts/__init__.py
odoo/addons/account_move_line_contra_accounts/__manifest__.py
odoo/addons/account_move_line_contra_accounts/i18n/de.po
odoo/addons/account_move_line_contra_accounts/images/screen.png
odoo/addons/account_move_line_contra_accounts/models/__init__.py
odoo/addons/account_move_line_contra_accounts/models/account_move_line.py
odoo/addons/account_move_line_contra_accounts/static/description/icon.png
odoo/addons/account_move_line_contra_accounts/static/description/index.html
odoo/addons/account_move_line_contra_accounts/views/account_move_line.xml
odoo_addon_account_move_line_contra_accounts-18.0.1.0.0.dist-info/METADATA
odoo_addon_account_move_line_contra_accounts-18.0.1.0.0.dist-info/WHEEL
odoo_addon_account_move_line_contra_accounts-18.0.1.0.0.dist-info/top_level.txt
odoo_addon_account_move_line_contra_accounts-18.0.1.0.0.dist-info/RECORD
